nomics/__init__.py
nomics/nomics.py
nomics/utils.py
py_nomics_client-1.0.0.dist-info/LICENSE
py_nomics_client-1.0.0.dist-info/METADATA
py_nomics_client-1.0.0.dist-info/WHEEL
py_nomics_client-1.0.0.dist-info/top_level.txt
py_nomics_client-1.0.0.dist-info/RECORD
